{"assets":{"2E8DE1ADBA40230804B8F0E566E76787":{"type":"texture","assetRequest":{"type":"slide","state":"outgoing"},"url":"assets/2E8DE1ADBA40230804B8F0E566E76787.png","width":720,"height":540},"7FF7193B16738CA7D9F80CE75BCDBE5B":{"type":"texture","assetRequest":{"type":"slide","state":"incoming"},"url":"assets/7FF7193B16738CA7D9F80CE75BCDBE5B.png","width":720,"height":540}},"events":[{"effects":[{"beginTime":0,"baseLayer":{"animations":[],"initialState":{"affineTransform":[1,0,0,1,0,0],"masksToBounds":true,"rotation":0,"scale":1,"position":{"pointX":360,"pointY":270},"width":720,"sublayerTransform":[1,0,0,0,0,1,0,0,0,0,1,0,0,0,0,1],"contentsRect":{"y":0,"x":0,"width":1,"height":1},"opacity":1,"edgeAntialiasingMask":0,"height":540,"hidden":false,"anchorPoint":{"pointX":0.5,"pointY":0.5}},"objectID":0,"layers":[{"animations":[],"initialState":{"affineTransform":[1,0,0,1,0,0],"masksToBounds":false,"rotation":0,"scale":1,"position":{"pointX":360,"pointY":270},"width":720,"sublayerTransform":[1,0,0,0,0,1,0,0,0,0,1,-0.0007001582493355197,0,0,0,1],"contentsRect":{"y":0,"x":0,"width":1,"height":1},"opacity":1,"edgeAntialiasingMask":15,"height":540,"hidden":false,"anchorPoint":{"pointX":0.5,"pointY":0.5}},"layers":[{"animations":[],"layers":[],"initialState":{"affineTransform":[1,0,0,1,0,0],"masksToBounds":false,"rotation":0,"scale":1,"position":{"pointX":360,"pointY":270},"width":720,"sublayerTransform":[1,0,0,0,0,1,0,0,0,0,1,0,0,0,0,1],"contentsRect":{"y":0,"x":0,"width":1,"height":1},"opacity":1,"edgeAntialiasingMask":0,"height":540,"hidden":false,"anchorPoint":{"pointX":0.5,"pointY":0.5}},"texture":"7FF7193B16738CA7D9F80CE75BCDBE5B"},{"animations":[{"from":{"scalar":false},"property":"hidden","beginTime":0,"to":{"scalar":true},"fillMode":"both","duration":0.01}],"layers":[],"initialState":{"affineTransform":[1,0,0,1,0,0],"masksToBounds":false,"rotation":0,"scale":1,"position":{"pointX":360,"pointY":270},"width":720,"sublayerTransform":[1,0,0,0,0,1,0,0,0,0,1,0,0,0,0,1],"contentsRect":{"y":0,"x":0,"width":1,"height":1},"opacity":1,"edgeAntialiasingMask":0,"height":540,"hidden":false,"anchorPoint":{"pointX":0.5,"pointY":0.5}},"texture":"2E8DE1ADBA40230804B8F0E566E76787"}]}]},"effects":[],"duration":0.01,"type":"transition","name":"none","objectID":0}],"automaticPlay":false,"hyperlinks":[{"url":"http://www.adamek.biz/php.php","targetRectangle":{"y":384.7345519065857,"x":539.0364591674804,"width":41.5440000000001,"height":29.24000000000001}},{"url":"http://www.adamek.biz/php.php","targetRectangle":{"y":384.7345519065857,"x":580.5804591674805,"width":29.25599999999997,"height":29.24000000000001}},{"url":"http://www.adamek.biz/php.php","targetRectangle":{"y":413.9745519065857,"x":222.5484591674805,"width":257.76,"height":29.24000000000001}}],"accessibility":[{"text":"*以PHP编程接口为例","targetRectangle":{"y":459.5032286643982,"x":27.60001134872437,"width":165.8100001527071,"height":22.00000007510152}},{"text":"实际应用中的HTTP代理类型","targetRectangle":{"y":27.5,"x":74.12503814697266,"width":358.39232,"height":34}},{"text":"image1.png","targetRectangle":{"y":10.25,"x":7.875039577484131,"width":57.37496185302734,"height":57.37503814697266}},{"text":"image2.png","targetRectangle":{"y":498.75,"x":265.25,"width":164.1250457763672,"height":33}},{"text":"￼","targetRectangle":{"y":501.3668456077576,"x":659.4490599632263,"width":31.9921875,"height":29.99609375}},{"text":"*","targetRectangle":{"y":162.5661406517029,"x":317.8855834007263,"width":6.832000203609482,"height":29}},{"text":"在线检查你当前所使用的HTTP代理类型：http://www.adamek.biz/php.php","targetRectangle":{"y":384.7345519065857,"x":93.02045916748045,"width":516.816,"height":58.48000000000002}}],"baseLayer":{"animations":[],"initialState":{"affineTransform":[1,0,0,1,0,0],"masksToBounds":true,"rotation":0,"scale":1,"position":{"pointX":360,"pointY":270},"width":720,"sublayerTransform":[1,0,0,0,0,1,0,0,0,0,1,0,0,0,0,1],"contentsRect":{"y":0,"x":0,"width":1,"height":1},"opacity":1,"edgeAntialiasingMask":0,"height":540,"hidden":false,"anchorPoint":{"pointX":0.5,"pointY":0.5}},"objectID":0,"layers":[{"animations":[],"initialState":{"affineTransform":[1,0,0,1,0,0],"masksToBounds":false,"rotation":0,"scale":1,"position":{"pointX":360,"pointY":270},"width":720,"sublayerTransform":[1,0,0,0,0,1,0,0,0,0,1,-0.0007001582493355197,0,0,0,1],"contentsRect":{"y":0,"x":0,"width":1,"height":1},"opacity":1,"edgeAntialiasingMask":15,"height":540,"hidden":false,"anchorPoint":{"pointX":0.5,"pointY":0.5}},"layers":[{"animations":[],"layers":[],"initialState":{"affineTransform":[1,0,0,1,0,0],"masksToBounds":false,"rotation":0,"scale":1,"position":{"pointX":360,"pointY":270},"width":720,"sublayerTransform":[1,0,0,0,0,1,0,0,0,0,1,0,0,0,0,1],"contentsRect":{"y":0,"x":0,"width":1,"height":1},"opacity":1,"edgeAntialiasingMask":0,"height":540,"hidden":false,"anchorPoint":{"pointX":0.5,"pointY":0.5}},"texture":"7FF7193B16738CA7D9F80CE75BCDBE5B"},{"animations":[{"from":{"scalar":false},"property":"hidden","beginTime":0,"to":{"scalar":true},"fillMode":"both","duration":0.01}],"layers":[],"initialState":{"affineTransform":[1,0,0,1,0,0],"masksToBounds":false,"rotation":0,"scale":1,"position":{"pointX":360,"pointY":270},"width":720,"sublayerTransform":[1,0,0,0,0,1,0,0,0,0,1,0,0,0,0,1],"contentsRect":{"y":0,"x":0,"width":1,"height":1},"opacity":1,"edgeAntialiasingMask":0,"height":540,"hidden":false,"anchorPoint":{"pointX":0.5,"pointY":0.5}},"texture":"2E8DE1ADBA40230804B8F0E566E76787"}]}]}}]}